hugo_gettext/__init__.py
hugo_gettext/cli.py
hugo_gettext/compilation.py
hugo_gettext/config.py
hugo_gettext/extraction/__init__.py
hugo_gettext/extraction/e_domain.py
hugo_gettext/extraction/index.py
hugo_gettext/extraction/renderer_hugo_i18n.py
hugo_gettext/generation/__init__.py
hugo_gettext/generation/g_domain.py
hugo_gettext/generation/g_lang.py
hugo_gettext/generation/index.py
hugo_gettext/generation/renderer_hugo_l10n.py
hugo_gettext/utils.py
hugo_gettext-0.6.0.dist-info/entry_points.txt
hugo_gettext-0.6.0.dist-info/LICENSES/CC-BY-SA-4.0.txt
hugo_gettext-0.6.0.dist-info/LICENSES/CC0-1.0.txt
hugo_gettext-0.6.0.dist-info/LICENSES/LGPL-2.1-or-later.txt
hugo_gettext-0.6.0.dist-info/WHEEL
hugo_gettext-0.6.0.dist-info/METADATA
hugo_gettext-0.6.0.dist-info/RECORD
