Metadata-Version: 2.1
Name: hugo-gettext
Version: 0.6.0
Summary: I18n with gettext for Hugo
Home-page: https://github.com/phunh/hugo-gettext
License: LGPL-2.1-or-later
Author: Phu Hung Nguyen
Author-email: phuhnguyen@outlook.com
Requires-Python: >=3.8,<4.0
Classifier: Development Status :: 3 - Alpha
Classifier: Intended Audience :: Developers
Classifier: License :: OSI Approved
Classifier: Programming Language :: Python
Classifier: Programming Language :: Python :: 3
Classifier: Programming Language :: Python :: 3.10
Classifier: Programming Language :: Python :: 3.8
Classifier: Programming Language :: Python :: 3.9
Classifier: Topic :: Software Development :: Internationalization
Requires-Dist: markdown-gettext (>=0.2.1,<0.3.0)
Requires-Dist: mdit-py-hugo (>=0.3.1,<0.4.0)
Requires-Dist: mdit-py-i18n (>=0.2.1,<0.3.0)
Requires-Dist: tomlkit (>=0.12.1,<0.13.0)
Project-URL: Repository, https://github.com/phunh/hugo-gettext
